Lab1/sc2_block.v
// Complete the sc2_block module in this file
// Don't put any code in this file besides the sc2_block
// Refer to sc_block.v for hints!

module sc2_block(s, cout, a, b, cin);
    output s, cout;
    input a, b, cin;
    wire w1, w2, w3;

    xor xo1(w1, a, b);
    xor xo2(s, w1, cin);
    and a1(w2, a, b);
    and a2(w3, w1, cin);
    or  o1(cout, w2, w3);

endmodule // sc2_block

Lab1/sc2_block_tb.v
//Write your test bench for sc2_block here.
//Refer to sc_block_tb.v for formatting!
module sc2_test;
    reg a, b, cin;
    wire s, cout;

    sc2_block sc2 (s, cout, a, b, cin);

    initial begin
	    $dumpfile("sc2.vcd");
	    $dumpvars(0,sc2_test);

	    a = 0; b = 0; cin = 0; # 10;
	    a = 0; b = 0; cin = 1; # 10;
	    a = 0; b = 1; cin = 0; # 10;
	    a = 0; b = 1; cin = 1; # 10;
	    a = 1; b = 0; cin = 0; # 10;
	    a = 1; b = 0; cin = 1; # 10;
	    a = 1; b = 1; cin = 0; # 10;
	    a = 1; b = 1; cin = 1; # 10;

	    $finish;
    end

    initial 
	    $monitor("At time %2t, a = %d b =%d cin = %d s = %d cout = %d",
                     $time, a, b, cin, s, cout);

endmodule // sc2_test

Lab1/sc2.vcd
$date
	Sun Jan 26 14:59:50 2020
$end
$version
	Icarus Verilog
$end
$timescale
	1s
$end
$scope module sc2_test $end
$var wire 1 ! s $end
$var wire 1 " cout $end
$var reg 1 # a $end
$var reg 1 $ b $end
$var reg 1 % cin $end
$scope module sc2 $end
$var wire 1 # a $end
$var wire 1 $ b $end
$var wire 1 % cin $end
$var wire 1 " cout $end
$var wire 1 ! s $end
$var wire 1 & w1 $end
$var wire 1 ' w2 $end
$var wire 1 ( w3 $end
$upscope $end
$upscope $end
$enddefinitions $end
#0
$dumpvars
0(
0'
0&
0%
0$
0#
0"
0!
$end
#10
1!
1%
#20
1&
0%
1$
#30
1"
0!
1(
1%
#40
0"
1!
0(
0%
0$
1#
#50
1"
0!
1(
1%
#60
0(
0&
1'
0%
1$
#70
1!
1%
