Lab2/mux.v
// output is A (when control == 0) or B (when control == 1)
module mux2(out, A, B, control);
    output out;
    input  A, B;
    input  control;
    wire   wA, wB, not_control;
         
    not n1(not_control, control);
    and a1(wA, A, not_control);
    and a2(wB, B, control);
    or  o1(out, wA, wB);
endmodule // mux2

// output is A (when control == 00) or B (when control == 01) or
//           C (when control == 10) or D (when control == 11)
module mux4(out, A, B, C, D, control);
    output      out;
    input       A, B, C, D;
    input [1:0] control;
    wire        w0, w1;
    mux2 m0(w0, A, B, control[0]);
    mux2 m1(w1, C, D, control[0]);
    mux2 m2(out, w0, w1, control[1]);
    
endmodule // mux4

Lab2/logicunit.v
// 00 -> AND, 01 -> OR, 10 -> NOR, 11 -> XOR
module logicunit(out, A, B, control);
    output      out;
    input       A, B;
    input [1:0] control;
    wire w0, w1, w2, w3;

    and a1(w0, A, B);
    or  o1(w1, A, B);
    nor no1(w2, A, B);
    xor x1(w3, A, B);
    
    mux4 m1(out, w0, w1, w2, w3, control);

endmodule // logicunit

Lab2/alu1.v
module full_adder(sum, cout, a, b, cin);
    output sum, cout;
    input  a, b, cin;
    wire   partial_s, partial_c1, partial_c2;

    xor x0(partial_s, a, b);
    xor x1(sum, partial_s, cin);
    and a0(partial_c1, a, b);
    and a1(partial_c2, partial_s, cin);
    or  o1(cout, partial_c1, partial_c2);
endmodule // full_adder

`define ALU_UADD   3'h0
`define ALU_ADD    3'h2
`define ALU_SUB    3'h3
`define ALU_AND    3'h4
`define ALU_OR     3'h5
`define ALU_NOR    3'h6
`define ALU_XOR    3'h7

// 0xx -> arithmetic, 1xx -> logic
module alu1(out, carryout, A, B, carryin, control);
    output      out, carryout;
    input       A, B, carryin;
    input [2:0] control;
    wire        fa_b, sum, lu_out;
    
    xor xo1(fa_b, B, control[0]); 
    full_adder fa1(sum, carryout, A, fa_b, carryin);
    logicunit l1(lu_out, A, B, control[1:0]);
    mux2 m1(out, sum, lu_out, control[2]); 

endmodule // alu1

Lab2/alu1_tb.v
module alu1_test;
    // exhaustively test your 1-bit ALU implementation by adapting mux4_tb.v

    reg A = 0; 
    always #1 A = !A;
    reg B = 0;
    always #2 B = !B;
    reg carryin = 0;
    always #4 carryin = !carryin;
    
    reg [2:0] control = 0;

    initial begin 
	    $dumpfile("alu1.vcd");
	    $dumpvars(0, alu1_test);

	    # 8 control = 1;
	    # 8 control = 2;
	    # 8 control = 3;
	    # 8 control = 4;
	    # 8 control = 5;
	    # 8 control = 6;
	    # 8 control = 7;
	    # 8 $finish;
    end

    wire out, carryout;
    alu1 a1(out, carryout, A, B, carryin, control);
    /*
    initial begin
	    $display("A B cin s cout o");
	    $monitor("%d %d %d %d %d %d (at time %t)", A, B, carryin, control, carryout, out, $time);
    end
    */
endmodule

Lab2/alu1.vcd
$date
	Tue Feb  4 10:07:10 2020
$end
$version
	Icarus Verilog
$end
$timescale
	1s
$end
$scope module alu1_test $end
$var wire 1 ! out $end
$var wire 1 " carryout $end
$var reg 1 # A $end
$var reg 1 $ B $end
$var reg 1 % carryin $end
$var reg 3 & control [2:0] $end
$scope module a1 $end
$var wire 1 # A $end
$var wire 1 $ B $end
$var wire 1 % carryin $end
$var wire 3 ' control [2:0] $end
$var wire 1 ( fa_b $end
$var wire 1 ) sum $end
$var wire 1 ! out $end
$var wire 1 * lu_out $end
$var wire 1 " carryout $end
$scope module fa1 $end
$var wire 1 # a $end
$var wire 1 ( b $end
$var wire 1 % cin $end
$var wire 1 " cout $end
$var wire 1 + partial_c1 $end
$var wire 1 , partial_c2 $end
$var wire 1 - partial_s $end
$var wire 1 ) sum $end
$upscope $end
$scope module l1 $end
$var wire 1 # A $end
$var wire 1 $ B $end
$var wire 2 . control [1:0] $end
$var wire 1 / w0 $end
$var wire 1 0 w1 $end
$var wire 1 1 w2 $end
$var wire 1 2 w3 $end
$var wire 1 * out $end
$scope module m1 $end
$var wire 1 / A $end
$var wire 1 0 B $end
$var wire 1 1 C $end
$var wire 1 2 D $end
$var wire 2 3 control [1:0] $end
$var wire 1 4 w1 $end
$var wire 1 5 w0 $end
$var wire 1 * out $end
$scope module m0 $end
$var wire 1 / A $end
$var wire 1 0 B $end
$var wire 1 6 control $end
$var wire 1 7 not_control $end
$var wire 1 5 out $end
$var wire 1 8 wA $end
$var wire 1 9 wB $end
$upscope $end
$scope module m1 $end
$var wire 1 1 A $end
$var wire 1 2 B $end
$var wire 1 : control $end
$var wire 1 ; not_control $end
$var wire 1 4 out $end
$var wire 1 < wA $end
$var wire 1 = wB $end
$upscope $end
$scope module m2 $end
$var wire 1 5 A $end
$var wire 1 4 B $end
$var wire 1 > control $end
$var wire 1 ? not_control $end
$var wire 1 * out $end
$var wire 1 @ wA $end
$var wire 1 A wB $end
$upscope $end
$upscope $end
$upscope $end
$scope module m1 $end
$var wire 1 ) A $end
$var wire 1 * B $end
$var wire 1 B control $end
$var wire 1 C not_control $end
$var wire 1 ! out $end
$var wire 1 D wA $end
$var wire 1 E wB $end
$upscope $end
$upscope $end
$upscope $end
$enddefinitions $end
#0
$dumpvars
0E
0D
1C
0B
0A
0@
1?
0>
0=
1<
1;
0:
09
08
17
06
05
14
b0 3
02
11
00
0/
b0 .
0-
0,
0+
0*
0)
0(
b0 '
b0 &
0%
0$
0#
0"
0!
$end
#1
1!
1D
04
1)
0<
1-
10
01
12
1#
#2
1(
0#
1$
#3
1*
0!
1@
0D
15
0)
1"
18
0-
1+
1/
02
1#
#4
0*
0@
05
14
1!
0"
08
1<
1D
0+
0(
0/
00
11
1)
0#
0$
1%
#5
0!
0D
1"
04
0)
1,
0<
1-
10
01
12
1#
#6
1(
0#
1$
#7
1*
1!
1@
1D
15
1)
0,
18
0-
1+
1/
02
1#
#8
0*
0@
05
04
1!
07
0;
0"
08
0<
1D
16
1:
1-
0+
0/
00
11
1)
b1 .
b1 3
0#
0$
0%
b1 &
b1 '
#9
1*
0!
1@
0D
15
14
0)
1"
19
1=
0-
1+
10
01
12
1#
#10
0"
0+
0(
0#
1$
#11
1!
1D
04
1)
0=
1-
1/
02
1#
#12
0*
0@
05
0!
09
0D
1"
1(
0/
00
11
0)
1,
0#
0$
1%
#13
1*
1!
1@
1D
15
14
1)
0,
19
1=
0-
1+
10
01
12
1#
#14
0"
0+
0(
0#
1$
#15
0!
0D
1"
04
0)
1,
0=
1-
1/
02
1#
#16
1A
14
1*
1<
0@
05
0!
17
1;
0?
09
0D
0"
06
0:
1>
0-
0/
00
11
0)
0,
b10 .
b10 3
0#
0$
0%
b10 &
b10 '
#17
0*
1!
0A
1D
04
1)
0<
1-
10
01
12
1#
#18
1(
0#
1$
#19
0!
0D
15
0)
1"
18
0-
1+
1/
02
1#
#20
1*
1A
05
14
1!
0"
08
1<
1D
0+
0(
0/
00
11
1)
0#
0$
1%
#21
0*
0!
0A
0D
1"
04
0)
1,
0<
1-
10
01
12
1#
#22
1(
0#
1$
#23
1!
1D
15
1)
0,
18
0-
1+
1/
02
1#
#24
0*
0A
05
04
1!
07
0;
0"
08
0<
1D
16
1:
1-
0+
0/
00
11
1)
b11 .
b11 3
0#
0$
0%
b11 &
b11 '
#25
1*
0!
1A
0D
15
14
0)
1"
19
1=
0-
1+
10
01
12
1#
#26
0"
0+
0(
0#
1$
#27
0*
1!
0A
1D
04
1)
0=
1-
1/
02
1#
#28
05
0!
09
0D
1"
1(
0/
00
11
0)
1,
0#
0$
1%
#29
1*
1!
1A
1D
15
14
1)
0,
19
1=
0-
1+
10
01
12
1#
#30
0"
0+
0(
0#
1$
#31
0*
0!
0A
0D
1"
04
0)
1,
0=
1-
1/
02
1#
#32
14
1<
05
17
1;
1?
09
0"
06
0:
0>
0C
0-
0/
00
11
0)
0,
b0 .
b0 3
1B
0#
0$
0%
b100 &
b100 '
#33
04
1)
0<
1-
10
01
12
1#
#34
1(
0#
1$
#35
1!
1E
1*
1@
15
0)
1"
18
0-
1+
1/
02
1#
#36
0!
0E
0*
0@
05
14
0"
08
1<
0+
0(
0/
00
11
1)
0#
0$
1%
#37
1"
04
0)
1,
0<
1-
10
01
12
1#
#38
1(
0#
1$
#39
1!
1E
1*
1@
15
1)
0,
18
0-
1+
1/
02
1#
#40
0!
0E
0*
0@
05
04
07
0;
0"
08
0<
16
1:
1-
0+
0/
00
11
1)
b1 .
b1 3
0#
0$
0%
b101 &
b101 '
#41
1!
1E
1*
1@
15
14
0)
1"
19
1=
0-
1+
10
01
12
1#
#42
0"
0+
0(
0#
1$
#43
04
1)
0=
1-
1/
02
1#
#44
0!
0E
0*
0@
05
09
1"
1(
0/
00
11
0)
1,
0#
0$
1%
#45
1!
1E
1*
1@
15
14
1)
0,
19
1=
0-
1+
10
01
12
1#
#46
0"
0+
0(
0#
1$
#47
1"
04
0)
1,
0=
1-
1/
02
1#
#48
1!
1A
1E
14
1*
1<
0@
05
17
1;
0?
09
0"
06
0:
1>
0-
0/
00
11
0)
0,
b10 .
b10 3
0#
0$
0%
b110 &
b110 '
#49
0!
0E
0*
0A
04
1)
0<
1-
10
01
12
1#
#50
1(
0#
1$
#51
15
0)
1"
18
0-
1+
1/
02
1#
#52
1!
1E
1*
1A
05
14
0"
08
1<
0+
0(
0/
00
11
1)
0#
0$
1%
#53
0!
0E
0*
0A
1"
04
0)
1,
0<
1-
10
01
12
1#
#54
1(
0#
1$
#55
15
1)
0,
18
0-
1+
1/
02
1#
#56
0!
0E
0*
0A
05
04
07
0;
0"
08
0<
16
1:
1-
0+
0/
00
11
1)
b11 .
b11 3
0#
0$
0%
b111 &
b111 '
#57
1!
1E
1*
1A
15
14
0)
1"
19
1=
0-
1+
10
01
12
1#
#58
0"
0+
0(
0#
1$
#59
0!
0E
0*
0A
04
1)
0=
1-
1/
02
1#
#60
05
09
1"
1(
0/
00
11
0)
1,
0#
0$
1%
#61
1!
1E
1*
1A
15
14
1)
0,
19
1=
0-
1+
10
01
12
1#
#62
0"
0+
0(
0#
1$
#63
0!
0E
0*
0A
1"
04
0)
1,
0=
1-
1/
02
1#
#64
05
09
0"
1(
0/
00
11
1)
0,
0#
0$
0%
